CONTRIBUTOR
MANIFEST.in
README.rst
VERSION.md
requirements.txt
setup.py
snscli.py
snsgui.py
conf/channel.json.example
conf/pocket.json.example
snsapi/__init__.py
snsapi/async.py
snsapi/custom_conf.py
snsapi/errors.py
snsapi/platform.py
snsapi/snsbase.py
snsapi/snsconf.py
snsapi/snscrypt.py
snsapi/snslog.py
snsapi/snspocket.py
snsapi/snstype.py
snsapi/utils.py
snsapi.egg-info/PKG-INFO
snsapi.egg-info/SOURCES.txt
snsapi.egg-info/dependency_links.txt
snsapi.egg-info/requires.txt
snsapi.egg-info/top_level.txt
snsapi/data/init-channel.json.example
snsapi/data/snsgui.ini
snsapi/plugin/README.md
snsapi/plugin/__init__.py
snsapi/plugin/rss.py
snsapi/plugin/sina.py
snsapi/plugin/tencent.py
snsapi/plugin_trial/README.md
snsapi/plugin_trial/__init__.py
snsapi/plugin_trial/douban.py
snsapi/plugin_trial/emails.py
snsapi/plugin_trial/facebook.py
snsapi/plugin_trial/instagram.py
snsapi/plugin_trial/renren.py
snsapi/plugin_trial/sina_wap.py
snsapi/plugin_trial/sqlite.py
snsapi/plugin_trial/twitter.py
snsapi/third/PyRSS2Gen.py
snsapi/third/README.md
snsapi/third/__init__.py
snsapi/third/facebook.py
snsapi/third/feedparser.py
snsapi/third/oauth.py
snsapi/third/pyDes.py
snsapi/third/server.py
snsapi/third/timezone_sample.py
snsapi/third/twitter.py
snsapi/third/douban_client/__init__.py
snsapi/third/douban_client/client.py
snsapi/third/douban_client/api/__init__.py
snsapi/third/douban_client/api/album.py
snsapi/third/douban_client/api/base.py
snsapi/third/douban_client/api/book.py
snsapi/third/douban_client/api/comment.py
snsapi/third/douban_client/api/discussion.py
snsapi/third/douban_client/api/doumail.py
snsapi/third/douban_client/api/error.py
snsapi/third/douban_client/api/event.py
snsapi/third/douban_client/api/guess.py
snsapi/third/douban_client/api/miniblog.py
snsapi/third/douban_client/api/movie.py
snsapi/third/douban_client/api/music.py
snsapi/third/douban_client/api/note.py
snsapi/third/douban_client/api/online.py
snsapi/third/douban_client/api/photo.py
snsapi/third/douban_client/api/review.py
snsapi/third/douban_client/api/subject.py
snsapi/third/douban_client/api/user.py
