Metadata-Version: 1.1
Name: snsapi
Version: 0.8.1
Summary: lightweight middleware for multiple social networking services
Home-page: https://github.com/hupili/snsapi
Author: Pili Hu
Author-email: me@hupili.net
License: UNKNOWN
Platform: UNKNOWN
Classifier: License :: Public Domain
Classifier: Intended Audience :: Developers
Classifier: Intended Audience :: End Users/Desktop
Classifier: Intended Audience :: Science/Research
Classifier: Natural Language :: English
Classifier: Programming Language :: Python :: 2.7
Classifier: Development Status :: 4 - Beta
Classifier: Topic :: Software Development :: Libraries :: Python Modules
Classifier: Topic :: Communications :: Chat
Classifier: Topic :: Internet
Requires: oauth2 (>=1.5.211)
Requires: httplib2 (>=0.8)
Requires: python_dateutil (>=2.1)
Requires: lxml (>=2.3.2)
Requires: nose (>=1.3.0)
Provides: snsapi
